{
  "RepositoryId": "c8b2e117-de49-4e51-80b1-5dae3ad48c02",
  "Items": [
    {
      "$type": "FCms.Content.ContentFolderItem, FCms",
      "Childeren": [
        {
          "$type": "FCms.Content.StringContentItem, FCms",
          "Data": "Title value",
          "Id": "f12c105e-b4b4-44c0-8d75-9717ca21e448",
          "DefinitionId": "741be508-9bf2-40e6-b721-c2d8cc73ca95",
          "Filters": [],
          "ToolTip": null
        },
        {
          "$type": "FCms.Content.StringContentItem, FCms",
          "Data": "Subtitle Value",
          "Id": "60cfae67-4f20-40b5-bec2-11be594b2736",
          "DefinitionId": "89670657-6087-409e-9180-61763b90454a",
          "Filters": [],
          "ToolTip": null
        }
      ],
      "Id": "d5f5640e-0a9f-4a47-9042-a26729befc64",
      "DefinitionId": "80013e0d-868f-45fe-bd50-fe3714f529f7",
      "Filters": [],
      "ToolTip": null
    },
    {
      "$type": "FCms.Content.StringContentItem, FCms",
      "Data": "Test title",
      "Id": "14c9d315-ec74-4f7d-82b5-3633a59ef026",
      "DefinitionId": "5dbe3fe9-531c-4343-ba14-0b5165224df7",
      "Filters": [],
      "ToolTip": null
    }
  ]
}